cumin/__init__.py
cumin/__main__.py
cumin/api.py
cumin/cli.py
cumin/client.py
cumin/config.py
cumin/sse.py
cumin/utils.py
salt_cumin-0.7.dist-info/LICENSE
salt_cumin-0.7.dist-info/METADATA
salt_cumin-0.7.dist-info/WHEEL
salt_cumin-0.7.dist-info/entry_points.txt
salt_cumin-0.7.dist-info/top_level.txt
salt_cumin-0.7.dist-info/RECORD
