Metadata-Version: 2.1
Name: salt-cumin
Version: 0.7
Summary: A CLI front-end to a running salt-api system
Home-page: https://github.com/AstraLuma/cumin
Author: Seth House
Author-email: shouse@saltstack.com
Maintainer: Jamie Bliss
Maintainer-email: jamie@ivyleav.es
License: UNKNOWN
Keywords: salt saltstack salt-extension
Platform: UNKNOWN
Classifier: Programming Language :: Python
Classifier: Programming Language :: Python :: 3
Classifier: Development Status :: 5 - Production/Stable
Classifier: Environment :: Console
Classifier: Intended Audience :: Developers
Classifier: Intended Audience :: Information Technology
Classifier: Intended Audience :: System Administrators
Classifier: License :: OSI Approved :: Apache Software License
Classifier: Operating System :: POSIX :: Linux
Classifier: Topic :: System :: Clustering
Classifier: Topic :: System :: Distributed Computing
Requires-Dist: requests
Provides-Extra: kerberos
Requires-Dist: requests-kerberos ; extra == 'kerberos'
